{
    "Name": "Cube",
    "Shapes" : [
        {
            "Id": "CubeId",
            "Name": "Cube",
            "Type": "CUBE",
            "L": 1,
            "W": 1,
            "H": 1,
            "Color": {
                "red": 255,
                "green": 255,
                "blue": 0
            },
            "Transformation" :
            {
                "Translation" :{
                    "x": 0,
                    "y": 0,
                    "z": 0
                }
            }
        }
    ],
    "Aggregators" :[
        {
            "Name": "Cube",
            "ShapeIds" :[
                "CubeId"
            ]
        }
    ]
}